pyautomatic/1.py
pyautomatic/__init__.py
pyautomatic/download.py
pyautomatic/math.py
pyautomatic/pt.py
pyautomatic/rs1/__init__.py
pyautomatic/windows/__init__.py
pyautomatic/windows/media.py
pyautomatic/windows/reg.py
pyautomatic/windows/ui.py
pyautomatic/windows/windows.py
pyautomatic-1.0.3.dist-info/licenses/LICENSE
pyautomatic-1.0.3.dist-info/METADATA
pyautomatic-1.0.3.dist-info/WHEEL
pyautomatic-1.0.3.dist-info/top_level.txt
pyautomatic-1.0.3.dist-info/RECORD
