Metadata-Version: 2.4
Name: pyautomatic
Version: 1.0.3
Summary: A comprehensive Python automation toolkit for Windows
Author: xiaotbl
Author-email: monios114514@outlook.com
Project-URL: Bug Reports, https://github.com/cpumsconfig/pyautomatic/issues
Project-URL: Source, https://github.com/cpumsconfig/pyautomatic
Keywords: automation,windows,system-administration,win32,process-management,audio-control,encryption
Classifier: Programming Language :: Python :: 3
Classifier: Programming Language :: Python :: 3.7
Classifier: Programming Language :: Python :: 3.8
Classifier: Programming Language :: Python :: 3.9
Classifier: Programming Language :: Python :: 3.10
Classifier: Programming Language :: Python :: 3.11
Classifier: License :: Other/Proprietary License
Classifier: Operating System :: Microsoft :: Windows
Classifier: Operating System :: Microsoft :: Windows :: Windows 10
Classifier: Operating System :: Microsoft :: Windows :: Windows 11
Classifier: Development Status :: 4 - Beta
Classifier: Intended Audience :: Developers
Classifier: Topic :: Software Development :: Libraries :: Python Modules
Classifier: Topic :: System :: Systems Administration
Classifier: Topic :: Utilities
Requires-Python: >=3.7
License-File: LICENSE
Requires-Dist: pywin32>=300
Requires-Dist: psutil>=5.9.0
Requires-Dist: comtypes>=1.1.14
Requires-Dist: pycaw>=20181226
Requires-Dist: pycryptodome>=3.17.0
Requires-Dist: requests>=2.28.0
Requires-Dist: tqdm>=4.64.0
Provides-Extra: dev
Requires-Dist: pytest>=7.0.0; extra == "dev"
Requires-Dist: pytest-cov>=4.0.0; extra == "dev"
Requires-Dist: black>=22.0.0; extra == "dev"
Requires-Dist: flake8>=5.0.0; extra == "dev"
Provides-Extra: gui
Requires-Dist: PyQt5>=5.15.0; extra == "gui"
Requires-Dist: wxPython>=4.2.0; extra == "gui"
Dynamic: author
Dynamic: author-email
Dynamic: classifier
Dynamic: description
Dynamic: description-content-type
Dynamic: keywords
Dynamic: license-file
Dynamic: project-url
Dynamic: provides-extra
Dynamic: requires-dist
Dynamic: requires-python
Dynamic: summary
